kubex/__init__.py
kubex/__version__.py
kubex/py.typed
kubex/client/__init__.py
kubex/client/client.py
kubex/client/configuration.py
kubex/client/file_config.py
kubex/client/incluster_config.py
kubex/client/api/__init__.py
kubex/client/api/_logs.py
kubex/client/api/_metadata.py
kubex/client/api/_protocol.py
kubex/client/api/_subressource.py
kubex/client/api/api.py
kubex/core/__init__.py
kubex/core/exceptions.py
kubex/core/params.py
kubex/core/patch.py
kubex/core/request.py
kubex/core/response.py
kubex/core/subresource.py
kubex/core/request_builder/__init__.py
kubex/core/request_builder/builder.py
kubex/core/request_builder/constants.py
kubex/core/request_builder/logs.py
kubex/core/request_builder/metadata.py
kubex/core/request_builder/subresource.py
kubex/models/__init__.py
kubex/models/base.py
kubex/models/base_entity.py
kubex/models/interfaces.py
kubex/models/list_entity.py
kubex/models/metadata.py
kubex/models/namespace.py
kubex/models/partial_object_meta.py
kubex/models/pod.py
kubex/models/resource_config.py
kubex/models/scale.py
kubex/models/status.py
kubex/models/typing.py
kubex/models/watch_event.py
kubex-0.1.0a1.dist-info/METADATA
kubex-0.1.0a1.dist-info/WHEEL
kubex-0.1.0a1.dist-info/RECORD
