Metadata-Version: 2.3
Name: kubex
Version: 0.1.0a1
Summary: Asynchronous Kubernetes client inspired by kube.rs
Project-URL: Homepage, https://github.com/codemageddon/kubex
Project-URL: Repository, https://github.com/codemageddon/kubex.git
Project-URL: Issues, https://github.com/codemageddon/kubex/issues
Project-URL: Changelog, https://github.com/codemageddon/kubex/blob/main/CHANGELOG.md
Author-email: Codemageddon <dev@codemageddon.me>
Maintainer-email: Codemageddon <dev@codemageddon.me>
License: MIT License
Classifier: Development Status :: 3 - Alpha
Classifier: Intended Audience :: Developers
Classifier: License :: OSI Approved :: MIT License
Classifier: Programming Language :: Python :: 3
Classifier: Programming Language :: Python :: 3.10
Classifier: Programming Language :: Python :: 3.11
Classifier: Programming Language :: Python :: 3.12
Classifier: Programming Language :: Python :: 3.13
Classifier: Topic :: Software Development :: Build Tools
Requires-Python: >=3.10
Requires-Dist: httpx>=0.27.2
Requires-Dist: pydantic<3,>=2.0
Requires-Dist: pyyaml>=6.0.2
Provides-Extra: aiohttp
Requires-Dist: aiohttp>=3.11.2; extra == 'aiohttp'
